<?xml version="1.0" encoding="utf-8" ?>
<LanguageData>

  <!-- Friendly Descent -->
  <TSS_NarratorDescent_Friendly.label>叙事者降临（友好）</TSS_NarratorDescent_Friendly.label>
  <TSS_NarratorDescent_Friendly.letterLabel>叙事者降临</TSS_NarratorDescent_Friendly.letterLabel>
  <TSS_NarratorDescent_Friendly.letterText>叙事者决定以实体形态降临，为你提供协助。</TSS_NarratorDescent_Friendly.letterText>

  <!-- Hostile Descent -->
  <TSS_NarratorDescent_Hostile.label>叙事者降临（敌对）</TSS_NarratorDescent_Hostile.label>
  <TSS_NarratorDescent_Hostile.letterLabel>叙事者显现</TSS_NarratorDescent_Hostile.letterLabel>
  <TSS_NarratorDescent_Hostile.letterText>叙事者以充满敌意的形态显现，准备向你发起挑战！</TSS_NarratorDescent_Hostile.letterText>

</LanguageData>
